pygbif/__init__.py
pygbif/caching.py
pygbif/gbifissues.py
pygbif/gbifutils.py
pygbif/package_metadata.py
pygbif/collection/__init__.py
pygbif/collection/search.py
pygbif/institution/__init__.py
pygbif/institution/search.py
pygbif/literature/__init__.py
pygbif/literature/search.py
pygbif/maps/__init__.py
pygbif/maps/map.py
pygbif/occurrences/__init__.py
pygbif/occurrences/count.py
pygbif/occurrences/download.py
pygbif/occurrences/get.py
pygbif/occurrences/search.py
pygbif/registry/__init__.py
pygbif/registry/datasets.py
pygbif/registry/installations.py
pygbif/registry/networks.py
pygbif/registry/nodes.py
pygbif/registry/organizations.py
pygbif/species/__init__.py
pygbif/species/name_backbone.py
pygbif/species/name_lookup.py
pygbif/species/name_parser.py
pygbif/species/name_suggest.py
pygbif/species/name_usage.py
pygbif/utils/__init__.py
pygbif/utils/wkt_rewind.py
pygbif-0.6.6.dist-info/licenses/LICENSE
test/__init__.py
test/test-collection-search.py
test/test-institution-search.py
test/test-literature-search.py
test/test-maps-map.py
test/test-occurrences-count.py
test/test-occurrences-download_cancel.py
test/test-occurrences-download_citation.py
test/test-occurrences-download_describe.py
test/test-occurrences-download_get.py
test/test-occurrences-download_request.py
test/test-occurrences-download_sql.py
test/test-occurrences-get.py
test/test-occurrences-search.py
test/test-registry-dataset_metrics.py
test/test-registry-datasets.py
test/test-registry-installations.py
test/test-registry-networks.py
test/test-registry-nodes.py
test/test-registry-organizations.py
test/test-species-name-backbone.py
test/test-species-name_lookup.py
test/test-species-name_suggest.py
test/test-species-name_usage.py
test/test-wkt_rewind.py
pygbif-0.6.6.dist-info/METADATA
pygbif-0.6.6.dist-info/WHEEL
pygbif-0.6.6.dist-info/top_level.txt
pygbif-0.6.6.dist-info/RECORD
