Metadata-Version: 2.4
Name: pygbif
Version: 0.6.6
Summary: Python client for GBIF
Home-page: http://github.com/gbif/pygbif
Download-URL: https://github.com/gbif/pygbif/archive/refs/tags/v0.6.6.tar.gz
Author: Scott Chamberlain
Author-email: myrmecocystus@gmail.com
License: MIT
Keywords: gbif,biodiversity,specimens,API,web-services,occurrences,species,taxonomy
Classifier: Development Status :: 5 - Production/Stable
Classifier: Intended Audience :: Science/Research
Classifier: Topic :: Scientific/Engineering :: Bio-Informatics
Classifier: Natural Language :: English
Classifier: License :: OSI Approved :: MIT License
Classifier: Programming Language :: Python
Classifier: Programming Language :: Python :: 3.5
Classifier: Programming Language :: Python :: 3.6
Classifier: Programming Language :: Python :: 3.7
Classifier: Programming Language :: Python :: 3.8
Classifier: Programming Language :: Python :: 3.9
Classifier: Programming Language :: Python :: 3.10
Classifier: Programming Language :: Python :: 3.11
Classifier: Programming Language :: Python :: 3.12
License-File: LICENSE
Requires-Dist: requests>2.7
Requires-Dist: requests-cache
Requires-Dist: geojson_rewind
Requires-Dist: geomet
Requires-Dist: appdirs>=1.4.3
Requires-Dist: matplotlib
Dynamic: author
Dynamic: author-email
Dynamic: classifier
Dynamic: description
Dynamic: description-content-type
Dynamic: download-url
Dynamic: home-page
Dynamic: keywords
Dynamic: license
Dynamic: license-file
Dynamic: requires-dist
Dynamic: summary
